{"inkVersion":20,"root":[["^Salut toi","\n",{"->":"main"},["done",{"#f":5,"#n":"g-0"}],null],"done",{"main":[[["^Je m'entraine à communiquer","\n",["^Tu veux essayer ?","\n","ev","str","^Oui","/str","/ev",{"*":".^.c-0","flg":4},"ev","str","^Non","/str","/ev",{"*":".^.c-1","flg":4},{"c-0":["\n",{"->":"Agreed"},{"#f":5}],"c-1":["\n",{"->":"by"},{"#f":5}],"#f":5,"#n":"g-1"}],{"#f":5,"#n":"g-0"}],null],{"#f":1}],"Agreed":[[["^Ok lets go !","\n","ev","str","^MenuLang","/str",{"x()":"changeScene","exArgs":1},"pop","/ev","\n","end",{"#f":5,"#n":"g-0"}],null],{"#f":1}],"by":["^Pas grave, une prochaine fois","\n","end",{"#f":1}],"#f":1}],"listDefs":{}}